{
  "gitSyncId": "66ab5aca485a965425507d0c_2be84556-5183-4e65-8563-2c5be66b1177",
  "id": "Page1__$JSModule12$_JSModule1.myFun1",
  "isPublic": true,
  "moduleInstanceId": "Page1_JSModule12",
  "pluginId": "js-plugin",
  "pluginType": "JS",
  "rootModuleInstanceId": "Page1_JSModule12",
  "unpublishedAction": {
    "clientSideExecution": true,
    "collectionId": "Page1__$JSModule12$_JSModule1",
    "confirmBeforeExecute": false,
    "contextType": "PAGE",
    "datasource": {
      "isAutoGenerated": false,
      "name": "UNUSED_DATASOURCE",
      "pluginId": "js-plugin"
    },
    "executeOnLoad": false,
    "fullyQualifiedName": "_$JSModule12$_JSModule1.myFun1",
    "name": "myFun1",
    "pageId": "Page1",
    "userSetOnLoad": false
  }
}